NSC/__init__.py
NSC/api.py
NSC/due.py
NSC/version.py
NSC/tests/__init__.py
NSC/tests/test_api.py
pyNSC-0.1.dev0.dist-info/DESCRIPTION.rst
pyNSC-0.1.dev0.dist-info/METADATA
pyNSC-0.1.dev0.dist-info/RECORD
pyNSC-0.1.dev0.dist-info/WHEEL
pyNSC-0.1.dev0.dist-info/metadata.json
pyNSC-0.1.dev0.dist-info/top_level.txt
