Metadata-Version: 2.0
Name: pyNSC
Version: 0.1.dev0
Summary: NSC: a template for small scientific Python projects
Home-page: http://github.com/pynsc/pyNSC
Author: Michael Beyeler
Author-email: mbeyeler@uw.edu
Maintainer: Michael Beyeler
Maintainer-email: mbeyeler@uw.edu
License: MIT
Platform: OS Independent
Classifier: Development Status :: 3 - Alpha
Classifier: Environment :: Console
Classifier: Intended Audience :: Science/Research
Classifier: License :: OSI Approved :: MIT License
Classifier: Operating System :: OS Independent
Classifier: Programming Language :: Python
Classifier: Topic :: Scientific/Engineering
Requires: numpy
Requires-Dist: numpy
